echo_alpha
